README.md
setup.py
transmitter/constants.py
transmitter/main.py
witness_transmitter.egg-info/PKG-INFO
witness_transmitter.egg-info/SOURCES.txt
witness_transmitter.egg-info/dependency_links.txt
witness_transmitter.egg-info/entry_points.txt
witness_transmitter.egg-info/requires.txt
witness_transmitter.egg-info/top_level.txt