Metadata-Version: 1.0
Name: witness-transmitter
Version: 0.0.1
Summary: STEEM Witness updates made easy.
Home-page: http://github.com/emre/transmitter
Author: emre yilmaz
Author-email: mail@emreyilmaz.me
License: MIT
Platform: UNKNOWN
